Workbook

Sheet Resumo executivo
A1: RESUMO EXECUTIVO — SIMULADOR 5x2
A3: Indicador | B3: Valor | C3: Leitura
A4: HC atual (base enviada) | B4: =SUM('Simulador por loja'!C2:C31) -> 292 | C4: Soma das lojas listadas; comparar com consolidado corporativo de 292.
A5: Lideranças preenchidas | B5: =SUM('Simulador por loja'!D2:D31) -> 90 | C5: Há lojas sem informação de liderança; preencher para confirmar o total.
A6: Vendas médias mensais | B6: =SUM('Simulador por loja'!F2:F31) -> 22110779 | C6: Base informada como média mensal de jan–set/2026.
A7: HC recomendado estimado | B7: =SUM('Simulador por loja'!W2:W31) -> 269 | C7: Estimativa sujeita ao campo de unidades de cobertura simultâneas e validação por horário.
A8: Diferença estimada vs HC atual | B8: =SUM('Simulador por loja'!X2:X31) -> -23 | C8: Não interpretar como plano de contratação antes de validar turnos, líderes e jornadas.
A11: Decisões para a reunião
A12: 1. Validar a premissa de jornada semanal de 42 horas e os instrumentos legais/coletivos aplicáveis.
A13: 2. Confirmar a cobertura mínima de 3 pessoas em dias de baixo fluxo e 5 aos finais de semana por turno.
A14: 3. Preencher unidades de cobertura simultâneas e líderes reais por loja; não reduzir HC apenas por média de faturamento.
A15: 4. Simular escala diária, pausas e folgas; garantir liderança presente todos os dias.
A16: 5. Rodar piloto em lojas de HC enxuto e medir vendas/hora, conversão, atendimento, absenteísmo e horas extras.

Sheet Simulador por loja
A1: Canal | B1: Loja | C1: HC atual | D1: Líderes | F1: Vendas médias mensais (R$) | Jan-Set | G1: Metragem ² | H1: Média fluxo | I1: Abertura | J1: Fechamento | K1: Jornada Diária Sugerida | L1: Jornada de abertura sugerida | M1: Jornada de fechamento sugerida | N1: Unidades de cobertura simultâneas (input) | O1: Pessoas/turno seg-sex | P1: Pessoas/turno sáb-dom | Q1: Pessoa-dias/semana por unidade | R1: Composição seg-sex (abertura / fechamento) | S1: Composição sáb-dom (abertura / fechamento) | T1: HC operacional teórico | U1: HC operacional c/reserva | V1: Liderança mínima sugerida | W1: HC recomendado estimado | X1: Diferença vs HC atual | Y1: Vendas por HC atual (R$) | Z1: Vendas por HC recomendado (R$) | AA1: Recomendação de liderança | AB1: 3º turno sugerido? | AC1: Observações / validações
A2: Boutique | B2: Barra Shopping | C2: 9 | D2: 3 | F2: 1064306 | I2: 09:40 | J2: 22:14 | K2: 8:24 com 1h de intervalo | L2: 09:40–19:04 | M2: 12:50–22:14 | N2: 1 | O2: =IF(A2="Boutique",Premissas!$B$6,Premissas!$B$7) -> 4 | P2: =IF(A2="Boutique",Premissas!$B$8,Premissas!$B$9) -> 6 | Q2: =(Premissas!$B$12*O2+Premissas!$B$13*P2) -> 32 | R2: 1 VR + 2 vendedores / 1 gerente + 2 vendedores | S2: 1 líder + 4 vendedores / 1 líder + 4 vendedores | T2: =Q2/Premissas!$B$5 -> 6.4 | U2: =ROUNDUP(T2/(1-Premissas!$B$10),0) -> 9 | V2: =MAX(Premissas!$B$11,IF(D2="",Premissas!$B$11,D2)) -> 3 | W2: =MAX(U2,V2) -> 9 | X2: =W2-C2 -> 0 | Y2: =IFERROR(F2/C2,0) -> 118256.22 | Z2: =IFERROR(F2/W2,0) -> 118256.22 | AA2: Se líderes atuais <3: converter vaga de vendedor em subgerente; reserva recomendada também com perfil de liderança. | AB2: Avaliar reforço móvel em pico | AC2: Turno de abertura: 1 subgerente + 2 vendedores (seg-sex); fechamento idem. Fim de semana: 1 subgerente + 4 vendedores por turno. Reserva: 1 subgerente + 1 vendedor. Validar fluxo real, intervalos e CCT.
A3: Boutique | B3: BH Shop | C3: 9 | D3: 3 | F3: 672289 | I3: 09:40 | J3: 22:14 | K3: 8:24 com 1h de intervalo | L3: 09:40–18:24 | M3: 12:50–22:14 | N3: 1 | O3: =IF(A3="Boutique",Premissas!$B$6,Premissas!$B$7) -> 4 | P3: =IF(A3="Boutique",Premissas!$B$8,Premissas!$B$9) -> 6 | Q3: =(Premissas!$B$12*O3+Premissas!$B$13*P3) -> 32 | R3: 1 VR + 2 vendedores / 1 gerente + 2 vendedores | S3: 1 líder + 4 vendedores / 1 líder + 4 vendedores | T3: =Q3/Premissas!$B$5 -> 6.4 | U3: =ROUNDUP(T3/(1-Premissas!$B$10),0) -> 9 | V3: =MAX(Premissas!$B$11,IF(D3="",Premissas!$B$11,D3)) -> 3 | W3: =MAX(U3,V3) -> 9 | X3: =W3-C3 -> 0 | Y3: =IFERROR(F3/C3,0) -> 74698.778 | Z3: =IFERROR(F3/W3,0) -> 74698.778 | AA3: Se líderes atuais <3: converter vaga de vendedor em subgerente; reserva recomendada também com perfil de liderança. | AB3: Avaliar reforço móvel em pico | AC3: Turno de abertura: 1 subgerente + 2 vendedores (seg-sex); fechamento idem. Fim de semana: 1 subgerente + 4 vendedores por turno. Reserva: 1 subgerente + 1 vendedor. Validar fluxo real, intervalos e CCT.
A4: Boutique | B4: Cidade Jardim | C4: 7 | D4: 3 | F4: 367200 | I4: 09:40 | J4: 22:04 | K4: 8:24 com 1h de intervalo | L4: 09:40–19:04 | M4: 12:40–22:04 | N4: 1 | O4: 3 | P4: =IF(A4="Boutique",Premissas!$B$8,Premissas!$B$9) -> 6 | Q4: =(Premissas!$B$12*O4+Premissas!$B$13*P4) -> 27 | R4: 1 VR + 2 vendedores / 1 gerente + 2 vendedores | S4: 1 líder + 4 vendedores / 1 líder + 4 vendedores | T4: =Q4/Premissas!$B$5 -> 5.4 | U4: =ROUNDUP(T4/(1-Premissas!$B$10),0) -> 8 | V4: =MAX(Premissas!$B$11,IF(D4="",Premissas!$B$11,D4)) -> 3 | W4: =MAX(U4,V4) -> 8 | X4: =W4-C4 -> 1 | Y4: =IFERROR(F4/C4,0) -> 52457.143 | Z4: =IFERROR(F4/W4,0) -> 45900 | AA4: Se líderes atuais <3: converter vaga de vendedor em subgerente; reserva recomendada também com perfil de liderança. | AB4: Avaliar reforço móvel em pico | AC4: Turno de abertura: 1 subgerente + 2 vendedores (seg-sex); fechamento idem. Fim de semana: 1 subgerente + 4 vendedores por turno. Reserva: 1 subgerente + 1 vendedor. Validar fluxo real, intervalos e CCT.
A5: Boutique | B5: Higienópolis | C5: 8 | D5: 3 | F5: 639410 | I5: 09:40 | J5: 22:14 | K5: 8:24 com 1h de intervalo | L5: 09:40–19:04 | M5: 12:50–22:14 | N5: 1 | O5: =IF(A5="Boutique",Premissas!$B$6,Premissas!$B$7) -> 4 | P5: =IF(A5="Boutique",Premissas!$B$8,Premissas!$B$9) -> 6 | Q5: =(Premissas!$B$12*O5+Premissas!$B$13*P5) -> 32 | R5: 1 VR + 2 vendedores / 1 gerente + 2 vendedores | S5: 1 líder + 4 vendedores / 1 líder + 4 vendedores | T5: =Q5/Premissas!$B$5 -> 6.4 | U5: =ROUNDUP(T5/(1-Premissas!$B$10),0) -> 9 | V5: =MAX(Premissas!$B$11,IF(D5="",Premissas!$B$11,D5)) -> 3 | W5: =MAX(U5,V5) -> 9 | X5: =W5-C5 -> 1 | Y5: =IFERROR(F5/C5,0) -> 79926.25 | Z5: =IFERROR(F5/W5,0) -> 71045.556 | AA5: Se líderes atuais <3: converter vaga de vendedor em subgerente; reserva recomendada também com perfil de liderança. | AB5: Avaliar reforço móvel em pico | AC5: Turno de abertura: 1 subgerente + 2 vendedores (seg-sex); fechamento idem. Fim de semana: 1 subgerente + 4 vendedores por turno. Reserva: 1 subgerente + 1 vendedor. Validar fluxo real, intervalos e CCT.
A6: Boutique | B6: Iguatemi | C6: 12 | D6: 3 | F6: 1178273 | I6: 09:40 | J6: 22:20 | K6: 8:24 com 1h de intervalo | L6: 09:40–19:04 | M6: 12:56–22:20 | N6: 1 | O6: =IF(A6="Boutique",Premissas!$B$6,Premissas!$B$7) -> 4 | P6: =IF(A6="Boutique",Premissas!$B$8,Premissas!$B$9) -> 6 | Q6: =(Premissas!$B$12*O6+Premissas!$B$13*P6) -> 32 | R6: 1 VR + 2 vendedores / 1 gerente + 2 vendedores | S6: 1 líder + 4 vendedores / 1 líder + 4 vendedores | T6: =Q6/Premissas!$B$5 -> 6.4 | U6: =ROUNDUP(T6/(1-Premissas!$B$10),0) -> 9 | V6: =MAX(Premissas!$B$11,IF(D6="",Premissas!$B$11,D6)) -> 3 | W6: =MAX(U6,V6) -> 9 | X6: =W6-C6 -> -3 | Y6: =IFERROR(F6/C6,0) -> 98189.417 | Z6: =IFERROR(F6/W6,0) -> 130919.22 | AA6: Se líderes atuais <3: converter vaga de vendedor em subgerente; reserva recomendada também com perfil de liderança. | AB6: Avaliar reforço móvel em pico | AC6: Turno de abertura: 1 subgerente + 2 vendedores (seg-sex); fechamento idem. Fim de semana: 1 subgerente + 4 vendedores por turno. Reserva: 1 subgerente + 1 vendedor. Validar fluxo real, intervalos e CCT.
A7: Boutique | B7: Iguatemi Campinas | C7: 7 | D7: 3 | F7: 608086 | I7: 09:40 | J7: 22:04 | K7: 8:24 com 1h de intervalo | L7: 09:40–19:04 | M7: 12:40–22:04 | N7: 1 | O7: =IF(A7="Boutique",Premissas!$B$6,Premissas!$B$7) -> 4 | P7: =IF(A7="Boutique",Premissas!$B$8,Premissas!$B$9) -> 6 | Q7: =(Premissas!$B$12*O7+Premissas!$B$13*P7) -> 32 | R7: 1 VR + 2 vendedores / 1 gerente + 2 vendedores | S7: 1 líder + 4 vendedores / 1 líder + 4 vendedores | T7: =Q7/Premissas!$B$5 -> 6.4 | U7: =ROUNDUP(T7/(1-Premissas!$B$10),0) -> 9 | V7: =MAX(Premissas!$B$11,IF(D7="",Premissas!$B$11,D7)) -> 3 | W7: =MAX(U7,V7) -> 9 | X7: =W7-C7 -> 2 | Y7: =IFERROR(F7/C7,0) -> 86869.429 | Z7: =IFERROR(F7/W7,0) -> 67565.111 | AA7: Se líderes atuais <3: converter vaga de vendedor em subgerente; reserva recomendada também com perfil de liderança. | AB7: Avaliar reforço móvel em pico | AC7: Turno de abertura: 1 subgerente + 2 vendedores (seg-sex); fechamento idem. Fim de semana: 1 subgerente + 4 vendedores por turno. Reserva: 1 subgerente + 1 vendedor. Validar fluxo real, intervalos e CCT.
A8: Boutique | B8: JK Live | C8: 8 | D8: 3 | F8: 681683 | I8: 09:40 | J8: 22:14 | K8: 8:24 com 1h de intervalo | L8: 09:40–19:04 | M8: 12:50–22:14 | N8: 1 | O8: =IF(A8="Boutique",Premissas!$B$6,Premissas!$B$7) -> 4 | P8: =IF(A8="Boutique",Premissas!$B$8,Premissas!$B$9) -> 6 | Q8: =(Premissas!$B$12*O8+Premissas!$B$13*P8) -> 32 | R8: 1 VR + 2 vendedores / 1 gerente + 2 vendedores | S8: 1 líder + 4 vendedores / 1 líder + 4 vendedores | T8: =Q8/Premissas!$B$5 -> 6.4 | U8: =ROUNDUP(T8/(1-Premissas!$B$10),0) -> 9 | V8: =MAX(Premissas!$B$11,IF(D8="",Premissas!$B$11,D8)) -> 3 | W8: =MAX(U8,V8) -> 9 | X8: =W8-C8 -> 1 | Y8: =IFERROR(F8/C8,0) -> 85210.375 | Z8: =IFERROR(F8/W8,0) -> 75742.556 | AA8: Se líderes atuais <3: converter vaga de vendedor em subgerente; reserva recomendada também com perfil de liderança. | AB8: Avaliar reforço móvel em pico | AC8: Turno de abertura: 1 subgerente + 2 vendedores (seg-sex); fechamento idem. Fim de semana: 1 subgerente + 4 vendedores por turno. Reserva: 1 subgerente + 1 vendedor. Validar fluxo real, intervalos e CCT.
A9: Boutique | B9: Leblon | C9: 9 | D9: 3 | F9: 732025 | I9: 10:00 | J9: 22:00 | K9: 8:24 com 1h de intervalo | L9: 10:00–19:24 | M9: 12:36–22:00 | N9: 1 | O9: =IF(A9="Boutique",Premissas!$B$6,Premissas!$B$7) -> 4 | P9: =IF(A9="Boutique",Premissas!$B$8,Premissas!$B$9) -> 6 | Q9: =(Premissas!$B$12*O9+Premissas!$B$13*P9) -> 32 | R9: 1 VR + 2 vendedores / 1 gerente + 2 vendedores | S9: 1 líder + 4 vendedores / 1 líder + 4 vendedores | T9: =Q9/Premissas!$B$5 -> 6.4 | U9: =ROUNDUP(T9/(1-Premissas!$B$10),0) -> 9 | V9: =MAX(Premissas!$B$11,IF(D9="",Premissas!$B$11,D9)) -> 3 | W9: =MAX(U9,V9) -> 9 | X9: =W9-C9 -> 0 | Y9: =IFERROR(F9/C9,0) -> 81336.111 | Z9: =IFERROR(F9/W9,0) -> 81336.111 | AA9: Se líderes atuais <3: converter vaga de vendedor em subgerente; reserva recomendada também com perfil de liderança. | AB9: Avaliar reforço móvel em pico | AC9: Turno de abertura: 1 subgerente + 2 vendedores (seg-sex); fechamento idem. Fim de semana: 1 subgerente + 4 vendedores por turno. Reserva: 1 subgerente + 1 vendedor. Validar fluxo real, intervalos e CCT.
A10: Boutique | B10: Matalab | C10: 6 | D10: 3 | F10: 0 | I10: 11:00 | J10: 21:00 | K10: 8:24 com 1h de intervalo | L10: 11:00–20:24 | M10: 11:36–21:00 | N10: 1 | O10: =IF(A10="Boutique",Premissas!$B$6,Premissas!$B$7) -> 4 | P10: =IF(A10="Boutique",Premissas!$B$8,Premissas!$B$9) -> 6 | Q10: =(Premissas!$B$12*O10+Premissas!$B$13*P10) -> 32 | R10: 1 VR + 2 vendedores / 1 gerente + 2 vendedores | S10: 1 líder + 4 vendedores / 1 líder + 4 vendedores | T10: =Q10/Premissas!$B$5 -> 6.4 | U10: =ROUNDUP(T10/(1-Premissas!$B$10),0) -> 9 | V10: =MAX(Premissas!$B$11,IF(D10="",Premissas!$B$11,D10)) -> 3 | W10: =MAX(U10,V10) -> 9 | X10: =W10-C10 -> 3 | Y10: =IFERROR(F10/C10,0) -> 0 | Z10: =IFERROR(F10/W10,0) -> 0 | AA10: Se líderes atuais <3: converter vaga de vendedor em subgerente; reserva recomendada também com perfil de liderança. | AB10: Não fixar sem dado de fluxo | AC10: Turno de abertura: 1 subgerente + 2 vendedores (seg-sex); fechamento idem. Fim de semana: 1 subgerente + 4 vendedores por turno. Reserva: 1 subgerente + 1 vendedor. Validar fluxo real, intervalos e CCT.
A11: Boutique | B11: Morumbi | C11: 12 | D11: 3 | F11: 1181174 | I11: 09:40 | J11: 22:14 | K11: 8:24 com 1h de intervalo | L11: 09:40–19:04 | M11: 12:50–22:14 | N11: 1 | O11: =IF(A11="Boutique",Premissas!$B$6,Premissas!$B$7) -> 4 | P11: =IF(A11="Boutique",Premissas!$B$8,Premissas!$B$9) -> 6 | Q11: =(Premissas!$B$12*O11+Premissas!$B$13*P11) -> 32 | R11: 1 VR + 2 vendedores / 1 gerente + 2 vendedores | S11: 1 líder + 4 vendedores / 1 líder + 4 vendedores | T11: =Q11/Premissas!$B$5 -> 6.4 | U11: =ROUNDUP(T11/(1-Premissas!$B$10),0) -> 9 | V11: =MAX(Premissas!$B$11,IF(D11="",Premissas!$B$11,D11)) -> 3 | W11: =MAX(U11,V11) -> 9 | X11: =W11-C11 -> -3 | Y11: =IFERROR(F11/C11,0) -> 98431.167 | Z11: =IFERROR(F11/W11,0) -> 131241.56 | AA11: Se líderes atuais <3: converter vaga de vendedor em subgerente; reserva recomendada também com perfil de liderança. | AB11: Avaliar reforço móvel em pico | AC11: Turno de abertura: 1 subgerente + 2 vendedores (seg-sex); fechamento idem. Fim de semana: 1 subgerente + 4 vendedores por turno. Reserva: 1 subgerente + 1 vendedor. Validar fluxo real, intervalos e CCT.
A12: Boutique | B12: ParkShopping Brasília | C12: 8 | D12: 3 | F12: 616966 | I12: 09:40 | J12: 22:10 | K12: 8:24 com 1h de intervalo | L12: 09:40–19:04 | M12: 12:46–22:10 | N12: 1 | O12: =IF(A12="Boutique",Premissas!$B$6,Premissas!$B$7) -> 4 | P12: =IF(A12="Boutique",Premissas!$B$8,Premissas!$B$9) -> 6 | Q12: =(Premissas!$B$12*O12+Premissas!$B$13*P12) -> 32 | R12: 1 VR + 2 vendedores / 1 gerente + 2 vendedores | S12: 1 líder + 4 vendedores / 1 líder + 4 vendedores | T12: =Q12/Premissas!$B$5 -> 6.4 | U12: =ROUNDUP(T12/(1-Premissas!$B$10),0) -> 9 | V12: =MAX(Premissas!$B$11,IF(D12="",Premissas!$B$11,D12)) -> 3 | W12: =MAX(U12,V12) -> 9 | X12: =W12-C12 -> 1 | Y12: =IFERROR(F12/C12,0) -> 77120.75 | Z12: =IFERROR(F12/W12,0) -> 68551.778 | AA12: Se líderes atuais <3: converter vaga de vendedor em subgerente; reserva recomendada também com perfil de liderança. | AB12: Avaliar reforço móvel em pico | AC12: Turno de abertura: 1 subgerente + 2 vendedores (seg-sex); fechamento idem. Fim de semana: 1 subgerente + 4 vendedores por turno. Reserva: 1 subgerente + 1 vendedor. Validar fluxo real, intervalos e CCT.
A13: Outlet | B13: Aricanduva | C13: 6 | D13: 3 | F13: 324687 | I13: 09:40 | J13: 22:10 | K13: 8:24 com 1h de intervalo | L13: 09:40–19:04 | M13: 12:46–22:10 | N13: 1 | O13: =IF(A13="Boutique",Premissas!$B$6,Premissas!$B$7) -> 4 | P13: =IF(A13="Boutique",Premissas!$B$8,Premissas!$B$9) -> 6 | Q13: =(Premissas!$B$12*O13+Premissas!$B$13*P13) -> 32 | R13: 1 subgerente + 2 vendedores / 1 gerente + 2 vendedores | S13: 1 subgerente + 4 vendedores / 1 gerente + 4 vendedores | T13: =Q13/Premissas!$B$5 -> 6.4 | U13: =ROUNDUP(T13/(1-Premissas!$B$10),0) -> 9 | V13: =MAX(Premissas!$B$11,IF(D13="",Premissas!$B$11,D13)) -> 3 | W13: =MAX(U13,V13) -> 9 | X13: =W13-C13 -> 3 | Y13: =IFERROR(F13/C13,0) -> 54114.5 | Z13: =IFERROR(F13/W13,0) -> 36076.333 | AA13: Se líderes atuais <3: converter vaga de vendedor em subgerente; reserva recomendada também com perfil de liderança. | AB13: Avaliar reforço móvel em pico | AC13: Turno de abertura: 1 subgerente + 2 vendedores (seg-sex); fechamento idem. Fim de semana: 1 subgerente + 4 vendedores por turno. Reserva: 1 subgerente + 1 vendedor. Validar fluxo real, intervalos e CCT.
A14: Outlet | B14: A. Senna | C14: 12 | D14: 3 | F14: 717696 | I14: 09:00 | J14: 21:00 | K14: 8:24 com 1h de intervalo | L14: 09:00–18:24 | M14: 11:36–21:00 | N14: 1 | O14: =IF(A14="Boutique",Premissas!$B$6,Premissas!$B$7) -> 4 | P14: =IF(A14="Boutique",Premissas!$B$8,Premissas!$B$9) -> 6 | Q14: =(Premissas!$B$12*O14+Premissas!$B$13*P14) -> 32 | R14: 1 subgerente + 2 vendedores / 1 gerente + 2 vendedores | S14: 1 subgerente + 4 vendedores / 1 gerente + 4 vendedores | T14: =Q14/Premissas!$B$5 -> 6.4 | U14: =ROUNDUP(T14/(1-Premissas!$B$10),0) -> 9 | V14: =MAX(Premissas!$B$11,IF(D14="",Premissas!$B$11,D14)) -> 3 | W14: =MAX(U14,V14) -> 9 | X14: =W14-C14 -> -3 | Y14: =IFERROR(F14/C14,0) -> 59808 | Z14: =IFERROR(F14/W14,0) -> 79744 | AA14: Se líderes atuais <3: converter vaga de vendedor em subgerente; reserva recomendada também com perfil de liderança. | AB14: Avaliar reforço móvel em pico | AC14: Turno de abertura: 1 subgerente + 2 vendedores (seg-sex); fechamento idem. Fim de semana: 1 subgerente + 4 vendedores por turno. Reserva: 1 subgerente + 1 vendedor. Validar fluxo real, intervalos e CCT.
A15: Outlet | B15: Outlet Brasília | C15: 14 | D15: 3 | F15: 951435 | I15: 09:00 | J15: 21:00 | K15: 8:24 com 1h de intervalo | L15: 09:00–18:24 | M15: 11:36–21:00 | N15: 1 | O15: =IF(A15="Boutique",Premissas!$B$6,Premissas!$B$7) -> 4 | P15: =IF(A15="Boutique",Premissas!$B$8,Premissas!$B$9) -> 6 | Q15: =(Premissas!$B$12*O15+Premissas!$B$13*P15) -> 32 | R15: 1 subgerente + 2 vendedores / 1 gerente + 2 vendedores | S15: 1 subgerente + 4 vendedores / 1 gerente + 4 vendedores | T15: =Q15/Premissas!$B$5 -> 6.4 | U15: =ROUNDUP(T15/(1-Premissas!$B$10),0) -> 9 | V15: =MAX(Premissas!$B$11,IF(D15="",Premissas!$B$11,D15)) -> 3 | W15: =MAX(U15,V15) -> 9 | X15: =W15-C15 -> -5 | Y15: =IFERROR(F15/C15,0) -> 67959.643 | Z15: =IFERROR(F15/W15,0) -> 105715 | AA15: Se líderes atuais <3: converter vaga de vendedor em subgerente; reserva recomendada também com perfil de liderança. | AB15: Avaliar reforço móvel em pico | AC15: Turno de abertura: 1 subgerente + 2 vendedores (seg-sex); fechamento idem. Fim de semana: 1 subgerente + 4 vendedores por turno. Reserva: 1 subgerente + 1 vendedor. Validar fluxo real, intervalos e CCT.
A16: Outlet | B16: Outlet Butantã | C16: 10 | D16: 3 | F16: 647541 | I16: 09:40 | J16: 22:10 | K16: 8:24 com 1h de intervalo | L16: 09:40–19:04 | M16: 12:46–22:10 | N16: 1 | O16: =IF(A16="Boutique",Premissas!$B$6,Premissas!$B$7) -> 4 | P16: =IF(A16="Boutique",Premissas!$B$8,Premissas!$B$9) -> 6 | Q16: =(Premissas!$B$12*O16+Premissas!$B$13*P16) -> 32 | R16: 1 subgerente + 2 vendedores / 1 gerente + 2 vendedores | S16: 1 subgerente + 4 vendedores / 1 gerente + 4 vendedores | T16: =Q16/Premissas!$B$5 -> 6.4 | U16: =ROUNDUP(T16/(1-Premissas!$B$10),0) -> 9 | V16: =MAX(Premissas!$B$11,IF(D16="",Premissas!$B$11,D16)) -> 3 | W16: =MAX(U16,V16) -> 9 | X16: =W16-C16 -> -1 | Y16: =IFERROR(F16/C16,0) -> 64754.1 | Z16: =IFERROR(F16/W16,0) -> 71949 | AA16: Se líderes atuais <3: converter vaga de vendedor em subgerente; reserva recomendada também com perfil de liderança. | AB16: Avaliar reforço móvel em pico | AC16: Turno de abertura: 1 subgerente + 2 vendedores (seg-sex); fechamento idem. Fim de semana: 1 subgerente + 4 vendedores por turno. Reserva: 1 subgerente + 1 vendedor. Validar fluxo real, intervalos e CCT.
... A31: Outlet | B31: Outlet Shopping Light | C31: 11 | D31: 3 | F31: 825133 | I31: 09:00 | J31: 21:00 | K31: 8:24 com 1h de intervalo | L31: 09:00–18:24 | M31: 11:36–21:00 | N31: 1 | O31: =IF(A31="Boutique",Premissas!$B$6,Premissas!$B$7) -> 4 | P31: =IF(A31="Boutique",Premissas!$B$8,Premissas!$B$9) -> 6 | Q31: =(Premissas!$B$12*O31+Premissas!$B$13*P31) -> 32 | R31: 1 subgerente + 2 vendedores / 1 gerente + 2 vendedores | S31: 1 subgerente + 4 vendedores / 1 gerente + 4 vendedores | T31: =Q31/Premissas!$B$5 -> 6.4 | U31: =ROUNDUP(T31/(1-Premissas!$B$10),0) -> 9 | V31: =MAX(Premissas!$B$11,IF(D31="",Premissas!$B$11,D31)) -> 3 | W31: =MAX(U31,V31) -> 9 | X31: =W31-C31 -> -2 | Y31: =IFERROR(F31/C31,0) -> 75012.091 | Z31: =IFERROR(F31/W31,0) -> 91681.444 | AA31: Se líderes atuais <3: converter vaga de vendedor em subgerente; reserva recomendada também com perfil de liderança. | AB31: Avaliar reforço móvel em pico | AC31: Turno de abertura: 1 subgerente + 2 vendedores (seg-sex); fechamento idem. Fim de semana: 1 subgerente + 4 vendedores por turno. Reserva: 1 subgerente + 1 vendedor. Validar fluxo real, intervalos e CCT.
B32: TOTAL / CONSOLIDADO | C32: =SUM(C2:C31) -> 292 | D32: =SUM(D2:D31) -> 90 | F32: =SUM(F2:F31) -> 22110779 | W32: =SUM(W2:W31) -> 269 | X32: =SUM(X2:X31) -> -23 | Y32: — | Z32: —

Sheet Premissas
A1: SIMULADOR DE HC — MIGRAÇÃO PARA ESCALA 5x2
A3: Premissa | B3: Valor | C3: Orientação
A4: Jornada semanal (h) | B4: 42 | C4: Editável; jornada proposta informada para este cenário.
A5: Dias trabalhados por pessoa/semana | B5: 5 | C5: Escala 5x2.
A6: BTQ Cobertura baixa por turno (pessoas presentes) | B6: 4 | C6: Inclui liderança somente quando disponível para atendimento.
A7: OTL Cobertura baixa por turno (pessoas presentes) | B7: 4 | C7: Inclui liderança somente quando disponível para atendimento.
A8: BTQ Cobertura fim de semana por turno (pessoas presentes) | B8: 6 | C8: Aplicada a sábado e domingo.
A9: OTL Cobertura fim de semana por turno (pessoas presentes) | B9: 6 | C9: Aplicada a sábado e domingo.
A10: Reserva para férias/ausências | B10: 0.25 | C10: Hipótese inicial editável; substituir pela taxa histórica de RH.
A11: Lideranças mínimas por loja | B11: 3 | C11: Premissa de planejamento para cobrir os 7 dias com revezamento.
A12: Dias de baixo fluxo por semana | B12: 5 | C12: Modelo inicial: segunda a sexta; ajustar ao calendário real de fluxo.
A13: Dias de fim de semana por semana | B13: 2 | C13: Modelo inicial: sábado e domingo.
A14: Horas líquidas médias por turno/dia | C14: Informativo: recalcular jornadas a partir da abertura/fechamento e intervalos.
A17: Nota metodológica
A18: O simulador calcula uma estimativa agregada por loja e por unidade de cobertura/turno. A quantidade de turnos simultâneos e a distribuição real de pessoas por horário não constavam na base enviada; por isso, o campo 'Unidades de cobertura simultâneas' é editável e começa em 1. Ajuste-o conforme a necessidade real por loja.
A21: criar acelerador de vendas (comissão, premiação dif por nível de vendedor)
A22: turno intermediário
A23: consultoria de engajamento x pessoas felizes vendam mais
A24: Gi falar com shoppings sobre jornada de abertura de lojas
A25: lei e valor da multa por descumprir a regra
A26: não contratar tem custo, perco receita, pago multa ao shopping

Sheet Jornadas por loja
A1: Canal | B1: Loja | C1: Dia / cenário | D1: Turno | E1: Horário sugerido | F1: Mínimo de pessoas no turno | G1: Composição mínima | H1: Objetivo / regra
A2: Boutique | B2: Barra Shopping | C2: Segunda a sexta | D2: Abertura | E2: 09:40–19:04 | F2: 3 | G2: 1 subgerente + 2 vendedores | H2: A pessoa líder inicia junto à abertura; intervalo escalonado para manter cobertura.
A3: Boutique | B3: Barra Shopping | C3: Segunda a sexta | D3: Fechamento | E3: 12:50–22:14 | F3: 3 | G3: 1 subgerente + 2 vendedores | H3: A pessoa líder permanece até o fechamento; intervalo escalonado para manter cobertura.
A4: Boutique | B4: Barra Shopping | C4: Sábado e domingo | D4: Abertura | E4: 09:40–19:04 | F4: 5 | G4: 1 subgerente + 4 vendedores | H4: A pessoa líder inicia junto à abertura; intervalo escalonado para manter cobertura.
A5: Boutique | B5: Barra Shopping | C5: Sábado e domingo | D5: Fechamento | E5: 12:50–22:14 | F5: 5 | G5: 1 subgerente + 4 vendedores | H5: A pessoa líder permanece até o fechamento; intervalo escalonado para manter cobertura.
A6: Boutique | B6: Barra Shopping | C6: Pico / dias definidos | D6: 3º turno opcional | E6: 12:40–22:04 | F6: 1 | G6: 1 vendedor multifuncional | H6: Reforço opcional de pico; não incluído no HC-base. Ajustar ao fluxo por hora e ao limite semanal.
A7: Boutique | B7: BH Shop | C7: Segunda a sexta | D7: Abertura | E7: 09:00–18:24 | F7: 3 | G7: 1 subgerente + 2 vendedores | H7: A pessoa líder inicia junto à abertura; intervalo escalonado para manter cobertura.
A8: Boutique | B8: BH Shop | C8: Segunda a sexta | D8: Fechamento | E8: 12:50–22:14 | F8: 3 | G8: 1 subgerente + 2 vendedores | H8: A pessoa líder permanece até o fechamento; intervalo escalonado para manter cobertura.
A9: Boutique | B9: BH Shop | C9: Sábado e domingo | D9: Abertura | E9: 09:00–18:24 | F9: 5 | G9: 1 subgerente + 4 vendedores | H9: A pessoa líder inicia junto à abertura; intervalo escalonado para manter cobertura.
A10: Boutique | B10: BH Shop | C10: Sábado e domingo | D10: Fechamento | E10: 12:50–22:14 | F10: 5 | G10: 1 subgerente + 4 vendedores | H10: A pessoa líder permanece até o fechamento; intervalo escalonado para manter cobertura.
A11: Boutique | B11: BH Shop | C11: Pico / dias definidos | D11: 3º turno opcional | E11: 12:00–21:24 | F11: 1 | G11: 1 vendedor multifuncional | H11: Reforço opcional de pico; não incluído no HC-base. Ajustar ao fluxo por hora e ao limite semanal.
A12: Boutique | B12: Cidade Jardim | C12: Segunda a sexta | D12: Abertura | E12: 09:40–19:04 | F12: 3 | G12: 1 subgerente + 2 vendedores | H12: A pessoa líder inicia junto à abertura; intervalo escalonado para manter cobertura.
A13: Boutique | B13: Cidade Jardim | C13: Segunda a sexta | D13: Fechamento | E13: 12:40–22:04 | F13: 3 | G13: 1 subgerente + 2 vendedores | H13: A pessoa líder permanece até o fechamento; intervalo escalonado para manter cobertura.
... A151: Outlet | B151: Outlet Shopping Light | C151: Pico / dias definidos | D151: 3º turno opcional | E151: 12:00–21:00 | F151: 1 | G151: 1 vendedor multifuncional | H151: Reforço opcional de pico; não incluído no HC-base. Ajustar ao fluxo por hora e ao limite semanal.

Sheet Ativos
A1: Canal | B1: Empresa | C1: Centro de Custo | D1: Funcionário | E1: Cargo
A2: Outlet | B2: 033 - OUTLET IMIGRANTES | C2: OUTLET IMIGRANTES - 109035 | D2: ABNER HENRIQUE DOS ANJOS PEREIRA | E2: CONSULTOR (A) DE LOJA
A3: Outlet | B3: 023 - OUTLET AYRTON SENNA | C3: OUTLET AYRTON SENNA - 109024 | D3: ADRIANA APARECIDA GOMES | E3: CONSULTOR (A) DE LOJA
A4: Outlet | B4: 004 - OUTLET PREMIUM ITUPEVA | C4: OUTLET PREMMIUN ITUPEVA - 109005 | D4: ADRIANO GUILHERME RODRIGUES DA SILVA MELO | E4: CONSULTOR (A) DE LOJA
A5: Outlet | B5: 006 - OUTLET MOEMA | C5: OUTLET MOEMA - 109007 | D5: ALCIDES HERBERTO MARTINI | E5: GERENTE DE LOJA
A6: Outlet | B6: 006 - OUTLET MOEMA | C6: OUTLET MOEMA - 109007 | D6: ALESSANDRO SOARES SILVA | E6: CONSULTOR (A) DE LOJA
A7: Outlet | B7: 015 - OUTLET FORTALEZA | C7: OUTLET FORTALEZA - 109016 | D7: ALINE MACIEL DE SOUZA | E7: AUXILIAR DE VENDAS
A8: Outlet | B8: 016 - OUTLET CATARINA | C8: OUTLET CATARINA - 109017 | D8: ALINE QUITÉRIA DA SILVA | E8: GERENTE DE LOJA
A9: Outlet | B9: 006 - OUTLET MOEMA | C9: OUTLET MOEMA - 109007 | D9: AMANDA DA SILVA RAMOS | E9: CONSULTOR (A) DE LOJA
A10: Boutique | B10: 025 - BOUTIQUE BH SHOPPING | C10: BOUTIQUE BH SHOPPING - 109027 | D10: AMANDA FERREIRA BELIZARIO | E10: ESTOQUISTA
A11: Boutique | B11: 024 - BOUTIQUE PARK SHOP BRASILIA | C11: BOUTIQUE PARK SHOPPING BRASILIA - 109026 | D11: AMANDA LIMA DE OLIVEIRA | E11: AUXILIAR DE VENDAS
A12: Outlet | B12: 008 - OUTLET BRASILIA | C12: OUTLET BRASILIA - 109009 | D12: ANA CRISTINA PEREIRA PAZ FERREIRA | E12: CAIXA DE LOJA
... A278: Outlet | B278: 034 - OUTLET BH | C278: OUTLET POP UP BH - 109036 | D278: YAGO DE PAULA CARDOSO | E278: GERENTE DE LOJA
